{"dataURL":"file:\/\/\/Users\/alexandruandrei\/Developer\/zlocal_assets\/SwiftUI_Files\/project4-files\/BetterRest.csv","id":"49856C8D-BA1B-4878-8A87-B8652E4F077E","createdDate":"2021-04-07T18:54:32Z","title":"BetterRest.csv","modifiedDate":"2021-04-07T19:00:45Z","preferredFilename":"BetterRest","version":"1.0","dataResult":{"dataURL":"file:\/\/\/Users\/alexandruandrei\/Developer\/zlocal_assets\/SwiftUI_Files\/project4-files\/BetterRest.csv"},"activityEntities":["dataSourceTrainingStarted",[{"id":"722AEE56-97FE-466F-9C90-EC13540F431D","title":"Used By","createdDate":"2021-04-07T18:57:14Z","event":"dataSourceTrainingStarted","subtitle":"BetterRest 1"}],"dataSourceMetrics",[{"id":"44BD9EB6-4906-466A-BBF4-19EE0A553436","title":"Data Summary","createdDate":"2021-04-07T18:57:14Z","event":"dataSourceMetrics","subtitle":"10.000 Items"}]],"pathType":0,"experimentIDs":["20A6986A-117B-4E2A-BECB-A4820FCEDF9D","3F14AE49-C21C-47AD-9158-6B477C42DB95"]}